pep440cmp/__init__.py
pep440cmp/commands/__init__.py
pep440cmp/commands/is_prerelease.py
pep440cmp/commands/pep440cmp.py
pep440_version_compare_cli-1.0.10.dist-info/LICENSE
pep440_version_compare_cli-1.0.10.dist-info/METADATA
pep440_version_compare_cli-1.0.10.dist-info/WHEEL
pep440_version_compare_cli-1.0.10.dist-info/entry_points.txt
pep440_version_compare_cli-1.0.10.dist-info/top_level.txt
pep440_version_compare_cli-1.0.10.dist-info/zip-safe
pep440_version_compare_cli-1.0.10.dist-info/RECORD
