Metadata-Version: 2.1
Name: pep440-version-compare-cli
Version: 1.0.10
Summary: ``pkg_resources`` wrapper to compare versions using PEP 440 rules from the command line.
Home-page: https://github.com/hotoffthehamster/pep440-version-compare-cli
Author: HotOffThe Hamster
Author-email: hotoffthehamster+pep440cmp@gmail.com
License: MIT
Project-URL: Documentation, https://pep440-version-compare-cli.readthedocs.io/en/latest/
Project-URL: Source Code, https://github.com/hotoffthehamster/pep440-version-compare-cli
Keywords: library,configuration,settings,options,ini,conf,config
Platform: any
Classifier: License :: OSI Approved :: MIT License
Classifier: Development Status :: 5 - Production/Stable
Classifier: Intended Audience :: Developers
Classifier: Natural Language :: English
Classifier: Operating System :: OS Independent
Classifier: Programming Language :: Python :: 3
Classifier: Programming Language :: Python :: 3.8
Classifier: Programming Language :: Python :: 3.7
Classifier: Programming Language :: Python :: 3.6
Classifier: Programming Language :: Python :: 3.5
Classifier: Programming Language :: Python
Classifier: Topic :: Software Development :: Libraries :: Python Modules
Requires-Dist: click (<8,>=7.0)
